setup.py
devicehive_plugin_yingjun/__init__.py
devicehive_plugin_yingjun/api.py
devicehive_plugin_yingjun/api_event.py
devicehive_plugin_yingjun/api_handler.py
devicehive_plugin_yingjun/command.py
devicehive_plugin_yingjun/error.py
devicehive_plugin_yingjun/handler.py
devicehive_plugin_yingjun/message.py
devicehive_plugin_yingjun/notification.py
devicehive_plugin_yingjun/plugin.py
devicehive_plugin_yingjun/token.py
devicehive_plugin_yingjun/transport.py
devicehive_plugin_yingjun.egg-info/PKG-INFO
devicehive_plugin_yingjun.egg-info/SOURCES.txt
devicehive_plugin_yingjun.egg-info/dependency_links.txt
devicehive_plugin_yingjun.egg-info/requires.txt
devicehive_plugin_yingjun.egg-info/top_level.txt